odoo10_addon_sale_proforma_report-10.0.1.0.0-py2.7-nspkg.pth
odoo/addons/sale_proforma_report/README.rst
odoo/addons/sale_proforma_report/__init__.py
odoo/addons/sale_proforma_report/__manifest__.py
odoo/addons/sale_proforma_report/i18n/es.po
odoo/addons/sale_proforma_report/i18n/pt_BR.po
odoo/addons/sale_proforma_report/i18n/ro.po
odoo/addons/sale_proforma_report/i18n/sl.po
odoo/addons/sale_proforma_report/models/__init__.py
odoo/addons/sale_proforma_report/models/sale_order.py
odoo/addons/sale_proforma_report/static/description/icon.png
odoo/addons/sale_proforma_report/views/report_saleorder.xml
odoo/addons/sale_proforma_report/views/sale_order_view.xml
odoo10_addon_sale_proforma_report-10.0.1.0.0.dist-info/DESCRIPTION.rst
odoo10_addon_sale_proforma_report-10.0.1.0.0.dist-info/METADATA
odoo10_addon_sale_proforma_report-10.0.1.0.0.dist-info/RECORD
odoo10_addon_sale_proforma_report-10.0.1.0.0.dist-info/WHEEL
odoo10_addon_sale_proforma_report-10.0.1.0.0.dist-info/metadata.json
odoo10_addon_sale_proforma_report-10.0.1.0.0.dist-info/namespace_packages.txt
odoo10_addon_sale_proforma_report-10.0.1.0.0.dist-info/top_level.txt
