Metadata-Version: 2.0
Name: odoo10-addon-sale-proforma-report
Version: 10.0.1.0.0
Summary: Proforma report option in sale orders
Home-page: https://github.com/OCA/sale-reporting
Author: OdooMRP team,AvanzOSC,Tecnativa,Eficent
Author-email: UNKNOWN
License: UNKNOWN
Platform: UNKNOWN
Classifier: Programming Language :: Python :: 2.7
Classifier: Framework :: Odoo
Requires-Dist: odoo (<10.1dev,>=10.0)
